Workbook

Sheet Readme

Sheet Orders
A1: Order ID | B1: Date | C1: Customer ID | D1: Product ID | E1: Sales ID | F1: Qty | G1: Price | H1: Cost | I1: Revenue | J1: Total Cost | K1: Profit | L1: Product Name | M1: Category
A2: O001 | B2: 46023 | C2: C001 | D2: P001 | E2: S001 | F2: 2 | G2: =_xlfn.XLOOKUP(D2,Products!A:A,Products!D:D) -> 8500000 | H2: =_xlfn.XLOOKUP(D2,Products!A:A,Products!E:E) -> 7200000 | I2: =F2*G2 -> 17000000 | J2: =F2*H2 -> 14400000 | K2: =I2-J2 -> 2600000 | L2: =_xlfn.XLOOKUP(D2,Products!A:A,Products!B:B) -> Laptop A | M2: =_xlfn.XLOOKUP(D2,Products!A:A,Products!C:C) -> Laptop
A3: O002 | B3: 46023 | C3: C002 | D3: P003 | E3: S002 | F3: 5 | G3: =_xlfn.XLOOKUP(D3,Products!A:A,Products!D:D) -> 750000 | H3: =_xlfn.XLOOKUP(D3,Products!A:A,Products!E:E) -> 520000 | I3: =F3*G3 -> 3750000 | J3: =F3*H3 -> 2600000 | K3: =I3-J3 -> 1150000 | L3: =_xlfn.XLOOKUP(D3,Products!A:A,Products!B:B) -> Mechanical Keyboard | M3: =_xlfn.XLOOKUP(D3,Products!A:A,Products!C:C) -> Accessories
A4: O003 | B4: 46024 | C4: C003 | D4: P005 | E4: S003 | F4: 3 | G4: =_xlfn.XLOOKUP(D4,Products!A:A,Products!D:D) -> 1250000 | H4: =_xlfn.XLOOKUP(D4,Products!A:A,Products!E:E) -> 980000 | I4: =F4*G4 -> 3750000 | J4: =F4*H4 -> 2940000 | K4: =I4-J4 -> 810000 | L4: =_xlfn.XLOOKUP(D4,Products!A:A,Products!B:B) -> SSD 1TB | M4: =_xlfn.XLOOKUP(D4,Products!A:A,Products!C:C) -> Storage
O5: Sum of Revenue | S5: Row Labels | T5: Sum of Revenue
O6: 24500000 | S6: Laptop A | T6: 17000000
S7: Mechanical Keyboard | T7: 3750000
S8: SSD 1TB | T8: 3750000
S9: Grand Total | T9: 24500000
O14: Row Labels | P14: Sum of Revenue | S14: Row Labels | T14: Sum of Profit
O15: S001 | P15: 17000000 | S15: Laptop A | T15: 2600000
O16: S002 | P16: 3750000 | S16: Mechanical Keyboard | T16: 1150000
O17: S003 | P17: 3750000 | S17: SSD 1TB | T17: 810000
O18: Grand Total | P18: 24500000 | S18: Grand Total | T18: 4560000
O22: Row Labels | P22: Sum of Qty
O23: P001 | P23: 2
O24: P003 | P24: 5
O25: P005 | P25: 3
O26: Grand Total | P26: 10

Sheet Products
A1: Product ID | B1: Product Name | C1: Category | D1: Price | E1: Cost
A2: P001 | B2: Laptop A | C2: Laptop | D2: 8500000 | E2: 7200000
A3: P002 | B3: Mouse Wireless | C3: Accessories | D3: 150000 | E3: 90000
A4: P003 | B4: Mechanical Keyboard | C4: Accessories | D4: 750000 | E4: 520000
A5: P004 | B5: Monitor 24" | C5: Monitor | D5: 2100000 | E5: 1700000
A6: P005 | B6: SSD 1TB | C6: Storage | D6: 1250000 | E6: 980000

Sheet Dashboard

Sheet SalesPerson
A1: Sales ID | B1: Salesperson | C1: Region
A2: S001 | B2: Andi | C2: Jakarta
A3: S002 | B3: Budi | C3: Bandung
A4: S003 | B4: Citra | C4: Surabaya
A5: S004 | B5: Dimas | C5: Medan
A6: S005 | B6: Eka | C6: Makassar

Sheet Customers
A1: Customer ID | B1: Customer Name | C1: City
A2: C001 | B2: PT Maju Jaya | C2: Jakarta
A3: C002 | B3: CV Nusantara | C3: Bandung
A4: C003 | B4: PT Sejahtera | C4: Surabaya
A5: C004 | B5: PT Digital | C5: Medan
A6: C005 | B6: UD Makmur | C6: Makassar
